mai2_pcount/__init__.py
mai2_pcount/__main__.py
mai2_pcount-0.2.3.dist-info/LICENSE
mai2_pcount-0.2.3.dist-info/METADATA
mai2_pcount-0.2.3.dist-info/WHEEL
mai2_pcount-0.2.3.dist-info/RECORD
