Metadata-Version: 2.1
Name: mai2_pcount
Version: 0.2.3
Summary: wmc的机厅在线人数信息查询、修改插件~
Home-page: https://github.com/shengwang52005/mai2_pcount
License: MIT
Author: Miaowing
Author-email: shengwang52005@163.com
Requires-Python: >=3.10,<4.0
Classifier: License :: OSI Approved :: MIT License
Classifier: Programming Language :: Python :: 3
Classifier: Programming Language :: Python :: 3.10
Classifier: Programming Language :: Python :: 3.11
Classifier: Programming Language :: Python :: 3.12
Requires-Dist: nonebot-adapter-onebot (>=2.3.1)
Requires-Dist: nonebot-plugin-localstore (>=0.1.0)
Requires-Dist: nonebot2 (>=2.3.2)
Project-URL: Repository, https://github.com/shengwang52005/mai2_pcount
